gitpuller/__init__.py
gitpuller/gitpull.py
gitpuller/utils.py
salla_gitpuller-0.1.2.dist-info/licenses/LICENSE
salla_gitpuller-0.1.2.dist-info/METADATA
salla_gitpuller-0.1.2.dist-info/WHEEL
salla_gitpuller-0.1.2.dist-info/top_level.txt
salla_gitpuller-0.1.2.dist-info/RECORD
