Metadata-Version: 2.4
Name: salla_gitpuller
Version: 0.1.2
Summary: A lightweight utility to git pull a repository using SSH deploy keys stored in environment variables
Author-email: Muhammad Zahid <zahidmuhammad127@gmail.com>
License: MIT
Project-URL: Homepage, https://github.com/Zahid07/gitpuller
License-File: LICENSE
Dynamic: license-file
